LICENSE.txt
README.md
setup.py
photoEncryption/__init__.py
photoEncryption/decrypt.py
photoEncryption/encrypt.py
photoencryption.egg-info/PKG-INFO
photoencryption.egg-info/SOURCES.txt
photoencryption.egg-info/dependency_links.txt
photoencryption.egg-info/requires.txt
photoencryption.egg-info/top_level.txt