Metadata-Version: 2.1
Name: photoencryption
Version: 1.0.1
Summary: Encrypting and decrypting messages from images
Author: Bruno Faliszewski
License: MIT
Project-URL: homepage, https://github.com/BrunoFaliszewski/PhotoEncryption
Platform: UNKNOWN
License-File: LICENSE.txt
